gocam/__init__.py
gocam/_version.py
gocam/cli.py
gocam/utils.py
gocam/datamodel/__init__.py
gocam/datamodel/gocam.py
gocam/indexing/Flattener.py
gocam/indexing/Indexer.py
gocam/indexing/__init__.py
gocam/schema/gocam.yaml
gocam/translation/__init__.py
gocam/translation/minerva_wrapper.py
gocam/translation/tbox_translator.py
gocam/translation/cx2/__init__.py
gocam/translation/cx2/main.py
gocam/translation/cx2/style.py
gocam/translation/networkx/__init__.py
gocam/translation/networkx/graph_translator.py
gocam/translation/networkx/model_network_translator.py
gocam/vocabulary/__init__.py
gocam/vocabulary/taxa.py
gocam-0.6.0.dist-info/METADATA
gocam-0.6.0.dist-info/WHEEL
gocam-0.6.0.dist-info/entry_points.txt
gocam-0.6.0.dist-info/licenses/LICENSE
gocam-0.6.0.dist-info/RECORD
