Metadata-Version: 2.4
Name: gocam
Version: 0.6.0
Summary: GO CAM Data Model (Python)
Author-email: The Gene Ontology Consortium <help@geneontology.org>
License-File: LICENSE
Requires-Python: >=3.10
Requires-Dist: click<9,>=8
Requires-Dist: linkml-runtime<2,>=1.1.24
Requires-Dist: prefixmaps<0.3,>=0.2.6
Requires-Dist: pydantic<3,>=2
Requires-Dist: pyyaml<7,>=6
Requires-Dist: requests<3,>=2
Provides-Extra: cx2
Requires-Dist: ndex2<4,>=3.9.0; extra == 'cx2'
Requires-Dist: networkx[extra]<4,>=3; extra == 'cx2'
Provides-Extra: oaklib
Requires-Dist: oaklib; extra == 'oaklib'
Provides-Extra: owl
Requires-Dist: py-horned-owl; extra == 'owl'
